[{"color_ID":"40","color_name":"Stillness","type":"0","color_coverImage":"44972016092917091170089582.jpg","color_thumbnailImage":"44972016092917095453695674.jpg","color_alpha":"70","color_coverColor":"3a7b7c","color_locationType":"-1","color_location":"12","color_statisticalID":"1290362","color_masterType":"-1","color_authorImage":"44972016092917084624792086.jpg","color_introductionAuthor":"iYan","color_introductionAuthorTitle":"\u5370\u8c61 \u4ea7\u54c1\u8bbe\u8ba1\u5e08 \u6444\u5f71\u5e08","color_introductionDetail":"Stillness\u6ee4\u955c \u627f\u8f7d\u7740\u62df\u771f\u7684\u80f6\u7247\u6548\u679c\uff0c\u91c7\u7528\u81ea\u7136\u7684\u8272\u8c03\u3001\u5fae\u5999\u7684\u8272\u504f\uff0c\u975e\u5e38\u5b9e\u7528\u4e8e\u5ba4\u5916\u3001\u65c5\u6e38\u3001\u751f\u6d3b\u7247\u6bb5\u7b49\u6444\u5f71\u4f5c\u54c1\u3002","color_introductionURL":"https:\/\/beauty-material.adnonstop.com\/API\/interphoto\/dashi_list_wap\/index.php?t=10","color_unlockWeixinImage":"","color_unlockWeixinTitle":"\u5c06\u8fdc\u65b9\u7684\u4f60\uff0c\u5b9a\u683c\u5728\u6211\u7684\u8bd7\u91cc\u3002","share_link":"https:\/\/beauty-material.adnonstop.com\/share\/interphoto\/filter_share_friend\/index.php?id=40&version=1.2.0","detail":"null","color_filter":{"filter_type":"0","table_pic":"70562017061211571685725859.png","blend":[]}},{"color_ID":"37","color_name":"\u82b1\u6837\u5e74\u534e","type":"0","color_coverImage":"2894201609291703505515434.jpg","color_thumbnailImage":"28942016092917035777406034.jpg","color_alpha":"70","color_coverColor":"eb9e3a","color_locationType":"-1","color_location":"9","color_statisticalID":"1291027","color_masterType":"1","color_authorImage":"28942016092917013110795095.jpg","color_introductionAuthor":"\u590f\u6c38\u5eb7","color_introductionAuthorTitle":"\u89c6\u89c9\u4e4b\u738b\uff0c\u56fd\u9645\u77e5\u540d\u6444\u5f71\u5e08\u3001\u8bbe\u8ba1\u5e08\u3001\u5bfc\u6f14\uff0c\u4ee3\u8868\u4f5c\u300a\u82b1\u6837\u5e74\u534e\u300b\u300a\u6625\u5149\u4e4d\u6cc4\u300b\u300a2046\u300b","color_introductionDetail":"\u300a\u6625\u5149\u4e4d\u6cc4\u300b\u300a\u82b1\u6837\u5e74\u534e\u300b\u7684\u8272\u8c03\uff0c\u5e76\u4e0d\u662f\u4ec0\u4e48\u79d8\u5bc6\uff0c\u5176\u5b9e\u5c31\u662fcross processing\uff0c\u90a3\u4e2a\u5e74\u4ee3\u5c06\u5e7b\u706f\u7247E\u7247\u51b2\u6210C\u7247\uff0c\u53cd\u5dee\u6781\u5927\uff0c\u6709\u4e00\u70b9\u504f\u7eff\u3002\u7535\u5f71\u672c\u8eab\u5c31\u662f\u751f\u6d3b\u7684\u6620\u5c04\uff0c\u4e00\u6837\u7684\u8272\u8c03\uff0c\u5927\u5bb6\u53ef\u4ee5\u5927\u80c6\u5730\u5c1d\u8bd5\u5c3d\u60c5\u73a9\uff0c\u65e5\u5149\u4e0b\uff0c\u95ea\u5149\u706f\u4e0b\uff0c\u660f\u6697\u73af\u5883\u4e2d\uff0c\u53ef\u80fd\u6700\u540e\u53c8\u6709\u53e6\u4e00\u79cd\u60ca\u559c\u3002","color_introductionURL":"https:\/\/beauty-material.adnonstop.com\/API\/interphoto\/dashi_list_wap\/index.php?t=1","color_unlockWeixinImage":"","color_unlockWeixinTitle":"\u201c\u89c6\u89c9\u4e4b\u738b\u201d\u590f\u6c38\u5eb7\uff0c\u8c03\u51fa\u300a\u6625\u5149\u4e4d\u6cc4\u300b\u7535\u5f71\u6ee4\u955c","share_link":"https:\/\/beauty-material.adnonstop.com\/share\/interphoto\/filter_share_friend\/index.php?id=37&version=1.2.0","detail":"null","color_filter":{"filter_type":"0","table_pic":"57322017061211561069453645.png","blend":[]}},{"color_ID":"34","color_name":"Texture","type":"0","color_coverImage":"67272016092916254210846281.jpg","color_thumbnailImage":"67272016092916262432438041.jpg","color_alpha":"70","color_coverColor":"65695c","color_locationType":"-1","color_location":"6","color_statisticalID":"1291024","color_masterType":"1","color_authorImage":"67272016092916245637769337.jpg","color_introductionAuthor":"\u5f20\u60a6","color_introductionAuthorTitle":"\u9876\u5c16\u65f6\u5c1a\u6444\u5f71\u5e08\u3001\u300a\u7231\u4e0a\u8d85\u6a21\u300b\u5bfc\u5e08","color_introductionDetail":"\u5f20\u60a6\u7684\u6444\u5f71\u4f5c\u54c1\u603b\u662f\u4fdd\u6301\u4e00\u79cd\u76f8\u5f53\u9ad8\u7ea7\u7684\u65f6\u5c1a\u8d28\u611f\uff0c\u9996\u6b21\u5236\u4f5c\u4e2a\u4eba\u6ee4\u955c\u8fd9\u4efd\u8d28\u611f\u5b8c\u5168\u4fdd\u7559\uff0c\u8ba9\u4f60\u7684\u751f\u6d3b\u4eba\u50cf\u77ac\u95f4\u63d0\u5347\u5230\u4e00\u7ebf\u6742\u5fd7\u7ea7\u522b\u3002","color_introductionURL":"https:\/\/beauty-material.adnonstop.com\/API\/interphoto\/dashi_list_wap\/index.php?t=22","color_unlockWeixinImage":"","color_unlockWeixinTitle":"\u9876\u5c16\u65f6\u5c1a\u6444\u5f71\u5e08\u3001\u300a\u7231\u4e0a\u8d85\u6a21\u300b\u5bfc\u5e08 \u5f20\u60a6\uff0c\u503e\u529b\u6253\u9020 \u5370\u8c61InterPhoto \u8d28\u611f\u6ee4\u955c","share_link":"https:\/\/beauty-material.adnonstop.com\/share\/interphoto\/filter_share_friend\/index.php?id=34&version=1.2.0","detail":"null","color_filter":{"filter_type":"0","table_pic":"50682017061211550668556450.png","blend":[]}},{"color_ID":"35","color_name":"\u9759\u8c27\u4e4b\u5883","type":"0","color_coverImage":"52082016092916542230560773.jpg","color_thumbnailImage":"52082016092916545164234218.jpg","color_alpha":"70","color_coverColor":"361c1d","color_locationType":"-1","color_location":"7","color_statisticalID":"1291025","color_masterType":"1","color_authorImage":"52082016092916533413858155.jpg","color_introductionAuthor":"\u5f20\u60a6","color_introductionAuthorTitle":"\u9876\u5c16\u65f6\u5c1a\u6444\u5f71\u5e08\u3001\u300a\u7231\u4e0a\u8d85\u6a21\u300b\u5bfc\u5e08","color_introductionDetail":"\u4e3a\u98ce\u666f\u52a0\u5165\u504f\u7ea2\u8272\u8c03\uff0c\u8ba9\u666e\u901a\u7684\u5927\u666f\u90fd\u62e5\u6709\u4e86\u4e00\u4e1d\u91ce\u5916\u7684\u5b81\u9759\u6c14\u8d28\uff0c\u4e0d\u540c\u4e8e\u5c0f\u6e05\u65b0\u7684\u6696\u610f\uff0c\u8fd9\u6837\u7684\u98ce\u666f\u662f\u6df1\u9083\u800c\u53c8\u9ad8\u51b7\u7684\uff0c\u5374\u6709\u7740\u53e6\u4e00\u79cd\u8131\u4fd7\u7684\u6c1b\u56f4\u3002","color_introductionURL":"https:\/\/beauty-material.adnonstop.com\/API\/interphoto\/dashi_list_wap\/index.php?t=21","color_unlockWeixinImage":"","color_unlockWeixinTitle":"\u9876\u5c16\u65f6\u5c1a\u6444\u5f71\u5e08\u3001\u300a\u7231\u4e0a\u8d85\u6a21\u300b\u5bfc\u5e08 \u5f20\u60a6\uff0c\u503e\u529b\u6253\u9020 \u5370\u8c61InterPhoto \u8d28\u611f\u6ee4\u955c","share_link":"https:\/\/beauty-material.adnonstop.com\/share\/interphoto\/filter_share_friend\/index.php?id=35&version=1.2.0","detail":"null","color_filter":{"filter_type":"0","table_pic":"3911201706121155258948678.png","blend":[]}},{"color_ID":"36","color_name":"Twilight","type":"0","color_coverImage":"Master_YuShuo_Cover1.jpg","color_thumbnailImage":"28972016092916574591294751.jpg","color_alpha":"70","color_coverColor":"6b7291","color_locationType":"-1","color_location":"8","color_statisticalID":"1291026","color_masterType":"1","color_authorImage":"35412016101816024915283688.jpg","color_introductionAuthor":"\u4f59\u7855","color_introductionAuthorTitle":"\u4e2d\u56fd\u7b2c\u4e00\u65f6\u5c1a\u89c6\u89c9\u7763\u5bfc\uff0c\u65f6\u5c1a\u5927\u7247\u7f14\u9020\u4e13\u5bb6","color_introductionDetail":"\u66ae\u5149\u5e26\u7740\u5e7d\u8c27\u7684\u795e\u79d8\u84dd\u8c03\uff0c\u5176\u5b9e\u662f\u5e0c\u671b\u5e26\u7ed9\u522b\u4eba\u7684\u611f\u89c9\u5438\u5f15\u5374\u96be\u4ee5\u6349\u6478\uff0c\u8fd9\u79cd\u795e\u79d8\u611f\u7528\u4e8e\u4eba\u50cf\u80fd\u63d0\u70bc\u51fa\u73af\u5883\u6c1b\u56f4\uff0c\u7528\u4e8e\u98ce\u5149\u80fd\u5f97\u5230\u51c0\u5316\uff0c\u5c31\u7b97\u7528\u4e8e\u81ea\u62cd\u4e5f\u975e\u5e38\u9002\u5408\u63d0\u5347\u6c14\u8d28\u3002","color_introductionURL":"https:\/\/beauty-material.adnonstop.com\/API\/interphoto\/dashi_list_wap\/index.php?t=23","color_unlockWeixinImage":"","color_unlockWeixinTitle":"\u9189\u5728\u4e2d\u56fd\u7b2c\u4e00\u65f6\u5c1a\u89c6\u89c9\u7763\u5bfc\u4f59\u7855\u7684\u795e\u79d8\u84dd\u8c03\u91cc","share_link":"https:\/\/beauty-material.adnonstop.com\/share\/interphoto\/filter_share_friend\/index.php?id=36&version=1.2.0","detail":"null","color_filter":{"filter_type":"0","table_pic":"73532017061211554389086574.png","blend":[]}},{"color_ID":"38","color_name":"Leslie","type":"0","color_coverImage":"33632016092917051415176988.jpg","color_thumbnailImage":"33632016092917052978132032.jpg","color_alpha":"70","color_coverColor":"121212","color_locationType":"-1","color_location":"10","color_statisticalID":"1291028","color_masterType":"1","color_authorImage":"33632016092917045682610093.jpg","color_introductionAuthor":"\u8bb8\u7199\u6b63","color_introductionAuthorTitle":"\u8bd7\u4eba\u6444\u5f71\u5e08\uff0c\u6a2a\u8de8\u65f6\u5c1a\u3001\u8bbe\u8ba1\u3001\u827a\u672f\u3001\u6444\u5f71\u754c\u7684\u4f20\u5947\u201c\u602a\u53d4\u53d4\u201d","color_introductionDetail":"\u201c\u9ed1\u767d\u662f\u6211\u7684\u6700\u7231\u3002\u201d\u539f\u59cb\u3001\u771f\u5b9e\u3001\u76f4\u89c9\u3001\u72b6\u6001\uff0c\u892a\u53bb\u4e00\u5207\u8272\u5f69\uff0c\u8d64\u88f8\u88f8\u5730\u76f4\u9762\u751f\u6d3b\uff0c\u5448\u73b0\u81ea\u5df1\u3002\u4e22\u6389\u6240\u6709\u751f\u6d3b\u7684\u63a9\u9970\uff0c\u5f53\u53ea\u5269\u9ed1\u767d\u7684\u65f6\u5019\uff0c\u771f\u5b9e\u53cd\u800c\u66f4\u663e\u6709\u8da3\u4e0e\u75af\u72c2\u3002","color_introductionURL":"https:\/\/beauty-material.adnonstop.com\/API\/interphoto\/dashi_list_wap\/index.php?t=12","color_unlockWeixinImage":"","color_unlockWeixinTitle":"\u4eba\u4e4b\u521d\uff0c\u6027\u672c\u52a8\u7269\uff0c\u892a\u53bb\u4e00\u5207\u8272\u5f69\uff0c\u53ea\u7559\u9ed1\u767d\u3002","share_link":"https:\/\/beauty-material.adnonstop.com\/share\/interphoto\/filter_share_friend\/index.php?id=38&version=1.2.0","detail":"null","color_filter":{"filter_type":"0","table_pic":"84842017061211563119377792.png","blend":[]}},{"color_ID":"33","color_name":"Retro","type":"0","color_coverImage":"59352016092916220434433325.jpg","color_thumbnailImage":"59352016092916222210720965.jpg","color_alpha":"70","color_coverColor":"22261a","color_locationType":"-1","color_location":"5","color_statisticalID":"1291023","color_masterType":"1","color_authorImage":"59352016092916215091618068.jpg","color_introductionAuthor":"\u6797\u6d77\u97f3","color_introductionAuthorTitle":"\u56fd\u9645\u65f6\u5c1a\u6444\u5f71\u5e08\u3001\u5c0f\u63d0\u7434\u5bb6","color_introductionDetail":"\u5e26\u7740\u80f6\u7247\u8d28\u611f\u7684\u8272\u8c03\uff0c\u4e0d\u540c\u4e8e\u4ee5\u5f80\u6240\u89c1\uff0c\u66f4\u91cd\u89c6\u8272\u5f69\u7684\u63a7\u5236\u548c\u5bf9\u6bd4\u7684\u8c03\u6574\uff0c\u8ba9\u4eba\u50cf\u66f4\u5177\u590d\u53e4\u65f6\u5c1a\u7684\u5473\u9053\u3002\u5982\u679c\u60f3\u8981\u5e26\u5165\u66f4\u591a\u590d\u53e4\u7684\u611f\u89c9\uff0c\u4e5f\u53ef\u4ee5\u914c\u60c5\u518d\u52a0\u4e00\u4e9b\u566a\u70b9\u3002","color_introductionURL":"https:\/\/beauty-material.adnonstop.com\/API\/interphoto\/dashi_list_wap\/index.php?t=35","color_unlockWeixinImage":"","color_unlockWeixinTitle":"\u6c14\u8d28\u624d\u5973\u6797\u6d77\u97f3\uff0c\u4e00\u89c1\u503e\u5fc3\u7684\u4e0d\u53ea\u662f\u6ee4\u955c\u3002","share_link":"https:\/\/beauty-material.adnonstop.com\/share\/interphoto\/filter_share_friend\/index.php?id=33&version=1.2.0","detail":"null","color_filter":{"filter_type":"0","table_pic":"78412017061211543319923566.png","blend":[]}},{"color_ID":"32","color_name":"\u6696\u98ce","type":"0","color_coverImage":"19972016092916165852284810.jpg","color_thumbnailImage":"19972016092916194284663880.jpg","color_alpha":"70","color_coverColor":"5e6253","color_locationType":"-1","color_location":"4","color_statisticalID":"1291022","color_masterType":"1","color_authorImage":"19972016092916164911146034.jpg","color_introductionAuthor":"\u6797\u6d77\u97f3","color_introductionAuthorTitle":"\u56fd\u9645\u65f6\u5c1a\u6444\u5f71\u5e08\u3001\u5c0f\u63d0\u7434\u5bb6","color_introductionDetail":"\u6de1\u6de1\u7684\u9ec4\uff0c\u6d45\u6d45\u5730\u8986\u76d6\u5728\u753b\u9762\u4e4b\u4e0a\uff0c\u5b89\u9759\u800c\u6e29\u6696\uff0c\u65e0\u8bba\u7528\u5728\u4eba\u50cf\u548c\u98ce\u666f\u90fd\u80fd\u589e\u6dfb\u6696\u611f\uff0c\u5e0c\u671b\u80fd\u4e3a\u4f60\u7684\u751f\u6d3b\u6ce8\u5165\u8fd9\u80a1\u9633\u5149\u822c\u7684\u6b63\u80fd\u91cf\u3002","color_introductionURL":"https:\/\/beauty-material.adnonstop.com\/API\/interphoto\/dashi_list_wap\/index.php?t=34","color_unlockWeixinImage":"","color_unlockWeixinTitle":"\u6c14\u8d28\u624d\u5973\u6797\u6d77\u97f3\uff0c\u4e00\u89c1\u503e\u5fc3\u7684\u4e0d\u53ea\u662f\u6ee4\u955c\u3002","share_link":"https:\/\/beauty-material.adnonstop.com\/share\/interphoto\/filter_share_friend\/index.php?id=32&version=1.2.0","detail":"null","color_filter":{"filter_type":"0","table_pic":"24182017061211540926009657.png","blend":[]}},{"color_ID":"31","color_name":"Planet","type":"0","color_coverImage":"74432016092916082057797888.jpg","color_thumbnailImage":"74432016092916083059475449.jpg","color_alpha":"100","color_coverColor":"65695c","color_locationType":"-1","color_location":"3","color_statisticalID":"1291021","color_masterType":"1","color_authorImage":"7443201609291607381572337.jpg","color_introductionAuthor":"\u9ece\u6653\u4eae","color_introductionAuthorTitle":"\u65f6\u5c1a\u6444\u5f71\u5e08\u53ca\u6444\u5f71\u827a\u672f\u5bb6\uff0cASTUDIO\u521b\u59cb\u4eba\uff0c\u51fa\u7248\u624b\u673a\u6444\u5f71\u753b\u518c\u300aLonely Planet\u300b","color_introductionDetail":"\u9ece\u6653\u4eae \u7684\u6444\u5f71\u4f5c\u54c1\u4eb2\u5207\u800c\u6e29\u6696\uff0c\u5c06\u9ad8\u9ad8\u5728\u4e0a\u7684\u660e\u661f\u62c9\u56de\u4eba\u95f4\uff0c\u8ba9\u4eba\u4eb2\u8fd1\u3002\u751f\u6d3b\u4e0a\u4ed6\u5e0c\u671b\u8fd9\u6b3ePlanet\u6ee4\u955c\u4e0d\u9700\u8981\u8fc7\u5ea6\u4fee\u9970\u7167\u7247\uff0c\u8981\u505a\u7684\u4ec5\u4ec5\u662f\u8fd8\u539f\u751f\u6d3b\u7684\u7eaf\u51c0\uff0c\u6240\u4ee5\u4e3a\u4e86\u8ba9\u753b\u9762\u66f4\u52a0\u5e72\u51c0\uff0c\u9009\u62e9\u5c06\u8272\u8c03\u7a0d\u5fae\u8c03\u84dd\u3002","color_introductionURL":"https:\/\/beauty-material.adnonstop.com\/API\/interphoto\/dashi_list_wap\/index.php?t=38","color_unlockWeixinImage":"","color_unlockWeixinTitle":"\u6070\u6070\u662f\u6700\u91cd\u8981\u7684\u77ac\u95f4\uff0c\u624d\u4e0d\u5e0c\u671b\u88ab\u8fc7\u5ea6\u4fee\u9970\u3002","share_link":"https:\/\/beauty-material.adnonstop.com\/share\/interphoto\/filter_share_friend\/index.php?id=31&version=1.2.0","detail":"null","color_filter":{"filter_type":"0","table_pic":"85472017061211534560012093.png","blend":[]}},{"color_ID":"29","color_name":"Gold Coast","type":"0","color_coverImage":"61132016092914050224770561.jpg","color_thumbnailImage":"6113201609291405067005710.jpg","color_alpha":"70","color_coverColor":"2f5644","color_locationType":"-1","color_location":"1","color_statisticalID":"1291019","color_masterType":"1","color_authorImage":"61132016092913455769899730.jpg","color_introductionAuthor":"\u6c64\u8f89","color_introductionAuthorTitle":"\u54c8\u82cf\u5927\u5e08\u3001\u56fd\u9645\u6700\u6709\u5f71\u54cd\u529b\u6444\u5f71\u5e08\u4e4b\u4e00\uff0c\u8363\u83b72016\u5e74\u6444\u5f71\u91d1\u50cf\u5956","color_introductionDetail":"\u65e5\u5e38\u751f\u6d3b\u4e2d\uff0c\u4f1a\u7528\u5230\u504f\u94dc\u9ec4\u7684\u8272\u8c03\uff0c\u52a0\u91cd\u7167\u7247\u7684\u753b\u9762\u611f\uff0c\u5c31\u50cf\u8fd9\u7ec4\u5728\u6d77\u4e0a\u968f\u62cd\u7684\u5e06\u8239\uff0c\u56e0\u4e3a\u52a0\u4e0a\u94dc\u9ec4\u8272\u6ee4\u955c\u540e\uff0c\u611f\u89c9\u4f1a\u66f4\u4e3a\u6709\u6df1\u5ea6\uff0c\u800c\u4e0d\u662f\u5e73\u65f6\u7684\u7f8e\u597d\u98ce\u5149\u611f\u89c9\uff0c\u8fd9\u4e5f\u662fGold Coast\u7684\u521d\u8877\uff0c\u5e0c\u671b\u4e3a\u7167\u7247\u6dfb\u52a0\u7684\u539a\u91cd\u611f\u3002","color_introductionURL":"https:\/\/beauty-material.adnonstop.com\/API\/interphoto\/dashi_list_wap\/index.php?t=36","color_unlockWeixinImage":"","color_unlockWeixinTitle":"\u9ec4\u91d1\u6d77\u5cb8\u7684\u8bd7\u60c5\u753b\u610f\uff0c\u63d0\u5347\u751f\u6d3b\u7684\u539a\u91cd\u611f","share_link":"https:\/\/beauty-material.adnonstop.com\/share\/interphoto\/filter_share_friend\/index.php?id=29&version=1.2.0","detail":"null","color_filter":{"filter_type":"0","table_pic":"4296201706121152384778047.png","blend":[]}},{"color_ID":"30","color_name":"\u4e00\u523b","type":"0","color_coverImage":"30752016092916060612879385.jpg","color_thumbnailImage":"30752016092916061219835598.jpg","color_alpha":"70","color_coverColor":"22261a","color_locationType":"-1","color_location":"2","color_statisticalID":"1291020","color_masterType":"1","color_authorImage":"30752016092916054947412032.jpg","color_introductionAuthor":"\u6c64\u8f89","color_introductionAuthorTitle":"\u54c8\u82cf\u5927\u5e08\u3001\u56fd\u9645\u6700\u6709\u5f71\u54cd\u529b\u6444\u5f71\u5e08\u4e4b\u4e00\uff0c\u8363\u83b72016\u5e74\u6444\u5f71\u91d1\u50cf\u5956","color_introductionDetail":"\u6c64\u8f89 \u57282\u5e74\u65f6\u95f4\u91cc\uff0c\u62cd\u4e0b\u4e86\u5f71\u54cd\u4e2d\u56fd\u7684\u4e00\u767e\u4f4d\u540d\u4eba\uff0c\u7528\u9ed1\u767d\uff0c\u628a\u5bf9\u6bd4\u5ea6\u8c03\u9ad8\uff0c\u628a\u753b\u9762\u4e2d\u7684\u5176\u4ed6\u5c42\u6b21\u90fd\u62bd\u6389\uff0c\u8ba9\u4eba\u4e13\u6ce8\u4e8e\u76f8\u4e2d\u4eba\u7684\u8868\u60c5\u795e\u6001\u3002\u8fd9\u6b21\u4ed6\u628a\u6700\u7ecf\u5178\u7684\u4eba\u7269\u9ed1\u767d\u8096\u50cf\u505a\u6210\u6ee4\u955c\uff0c\u8ba9\u4f60\u7684\u9ed1\u767d\u7167\u7247\u66f4\u5177\u51b2\u51fb\u529b\u3002","color_introductionURL":"https:\/\/beauty-material.adnonstop.com\/API\/interphoto\/dashi_list_wap\/index.php?t=37","color_unlockWeixinImage":"","color_unlockWeixinTitle":"\u6253\u9020\u6700\u5177\u5f71\u54cd\u300a\u4e2d\u56fd\u8138\u300b\u7684\u6c64\u8f89\uff0c\u8096\u50cf\u4e2d\u6700\u7eaf\u7cb9\u7684\u9ed1\u767d\u3002","share_link":"https:\/\/beauty-material.adnonstop.com\/share\/interphoto\/filter_share_friend\/index.php?id=30&version=1.2.0","detail":"null","color_filter":{"filter_type":"0","table_pic":"24412017061211532048997597.png","blend":[]}},{"color_ID":"39","color_name":"Botany","type":"0","color_coverImage":"68142016092917073180976852.jpg","color_thumbnailImage":"68142016092917074175264459.jpg","color_alpha":"70","color_coverColor":"2d484c","color_locationType":"-1","color_location":"11","color_statisticalID":"1291029","color_masterType":"-1","color_authorImage":"68142016092917062256656676.jpg","color_introductionAuthor":"Ming","color_introductionAuthorTitle":"\u5370\u8c61 \u4ea7\u54c1\u8bbe\u8ba1\u5e08 \u6444\u5f71\u5e08","color_introductionDetail":"\u5982\u679c\u4f60\u6e34\u671b\u4e00\u4e2a\u4f18\u96c5\u3001\u8010\u770b\u3001\u61c2\u4f60\u53c8\u4e0d\u6c89\u95f7\u7684\u4e2d\u6027\u8272\u6765\u6da6\u9970\u4f60\u7684\u7167\u7247\uff0c Botany \u4f1a\u662f\u4e00\u4e2a\u7edd\u4f73\u9009\u62e9\u3002\u5b83\u5c06\u7070\u8272\u7684\u9ad8\u96c5\u5185\u655b\u548c\u8910\u8272\u7684\u81ea\u7136\u6e29\u6696\u878d\u4e3a\u4e00\u4f53\uff0c\u6210\u4e3a\u4e00\u6b3e\u5e26\u6709\u6ce5\u571f\u6c14\u606f\u7684\u590d\u6742\u6696\u8272\u3002\u7070\u8910\u8272\u53ef\u4f4e\u8c03\u53ef\u5927\u6c14\uff0c\u53ef\u590d\u53e4\u53ef\u540e\u73b0\u4ee3\uff0c\u5728\u5404\u5f0f\u8096\u50cf\uff0c\u98ce\u666f\u6444\u5f71\u4e2d\u5f97\u5fc3\u5e94\u624b\uff0c\u6e38\u5203\u6709\u4f59\uff0c\u770b\u4f3c\u5e73\u51e1\uff0c\u5374\u5f88\u4e0d\u4e00\u822c\u3002","color_introductionURL":"https:\/\/beauty-material.adnonstop.com\/API\/interphoto\/dashi_list_wap\/index.php?t=2","color_unlockWeixinImage":"","color_unlockWeixinTitle":"\u590d\u53e4\u7684\u7070\u8910\u8272\uff0c\u4f18\u96c5\u8010\u770b\uff0c\u4e00\u8bd5\u5373\u71c3\/\u4e00\u8bd5\u4fbf\u7231\u4e0a","share_link":"https:\/\/beauty-material.adnonstop.com\/share\/interphoto\/filter_share_friend\/index.php?id=39&version=1.2.0","detail":"null","color_filter":{"filter_type":"0","table_pic":"75342017061211565692849188.png","blend":[]}},{"color_ID":"41","color_name":"Polychrome","type":"0","color_coverImage":"40612016092917171257244626.jpg","color_thumbnailImage":"52822016092917172098494714.jpg","color_alpha":"70","color_coverColor":"ad7347","color_locationType":"-1","color_location":"13","color_statisticalID":"1290372","color_masterType":"-1","color_authorImage":"40612016092917165596194763.jpg","color_introductionAuthor":"Kenven","color_introductionAuthorTitle":"\u5370\u8c61 \u4ea7\u54c1\u8bbe\u8ba1\u5e08","color_introductionDetail":"Polychrome\u6ee4\u955c\u975e\u5e38\u9002\u5408\u5728\u9633\u5149\u4ee5\u53ca\u5149\u6591\u5e95\u4e0b\u62cd\u6444\u7684\u7167\u7247\uff0c\u80fd\u8425\u9020\u51fa\u6070\u5230\u597d\u5904\u7684\u65f6\u5149\u98de\u901d\u7684\u6548\u679c\u6c1b\u56f4\u3002\u5176\u552f\u7f8e\u591a\u5f69\u7684\u8272\u8c03\uff0c\u4e3a\u65c5\u6e38\u3001\u98ce\u666f\u7b49\u751f\u6d3b\u7167\u7247\u8425\u9020\u8bd7\u4e0e\u8fdc\u65b9\u7684\u610f\u5883\u3002","color_introductionURL":"https:\/\/beauty-material.adnonstop.com\/API\/interphoto\/dashi_list_wap\/index.php?t=8","color_unlockWeixinImage":"","color_unlockWeixinTitle":"\u7528\u540c\u4e00\u4e2a\u6ee4\u955c\uff0c\u7b49\u4e00\u573a\u9082\u9005","share_link":"https:\/\/beauty-material.adnonstop.com\/share\/interphoto\/filter_share_friend\/index.php?id=41&version=1.2.0","detail":"null","color_filter":{"filter_type":"0","table_pic":"54612017061211574165501955.png","blend":[]}},{"color_ID":"42","color_name":"Journey","type":"0","color_coverImage":"79282016092917274576875813.jpg","color_thumbnailImage":"79282016092917275831690373.jpg","color_alpha":"70","color_coverColor":"fdfdff","color_locationType":"-1","color_location":"14","color_statisticalID":"1290374","color_masterType":"-1","color_authorImage":"79282016092917185294912412.jpg","color_introductionAuthor":"Killua Zaoldyeck","color_introductionAuthorTitle":"\u5370\u8c61 \u4ea7\u54c1\u8bbe\u8ba1\u5e08","color_introductionDetail":"Journey \u662f\u4e00\u79cd\u504f\u6d45\u7eff\u8272\u7684\u51b7\u8272\u8c03\u6ee4\u955c\uff0c\u8fd9\u79cd\u51b7\u989c\u8272\u7684\u6ee4\u955c\u5728\u89c6\u89c9\u4e0a\u4f1a\u4ea7\u751f\u4e00\u79cd\u6536\u7f29\u7684\u4f5c\u7528\uff0c\u7ed9\u4eba\u51c9\u723d\u5b89\u9759\u7684\u611f\u89c9\uff0c\u9002\u5408\u81ea\u7136\u3001\u98ce\u683c\u6444\u5f71\u7b49\u8272\u5f69\u7167\u7247\u3002","color_introductionURL":"https:\/\/beauty-material.adnonstop.com\/API\/interphoto\/dashi_list_wap\/index.php?t=14","color_unlockWeixinImage":"","color_unlockWeixinTitle":"\u590f\u65e5\u708e\u708e\uff0c\u7528\u9ad8\u51b7\u7684\u8272\u8c03\u6765\u964d\u964d\u6e29","share_link":"https:\/\/beauty-material.adnonstop.com\/share\/interphoto\/filter_share_friend\/index.php?id=42&version=1.2.0","detail":"null","color_filter":{"filter_type":"2","table_pic":"24752017061211580315035090.png","blend":[{"blend_pic":"Color_Blend_TheJourney.png","blend_alpha":"1.0","blend_type":"33"}]}},{"color_ID":"43","color_name":"\u9006\u4e16\u754c","type":"0","color_coverImage":"25202016092917285898026673.jpg","color_thumbnailImage":"252020160929172909647668.jpg","color_alpha":"70","color_coverColor":"596561","color_locationType":"-1","color_location":"15","color_statisticalID":"1290376","color_masterType":"-1","color_authorImage":"25202016092917284648158446.jpg","color_introductionAuthor":"G.A.O.","color_introductionAuthorTitle":"\u5370\u8c61 \u4ea7\u54c1\u8bbe\u8ba1\u5e08","color_introductionDetail":"\u9006\u4e16\u754c \u901a\u8fc7\u6a21\u4eff\u94f6\u76d0\u80f6\u7247\u7684\u6548\u679c\uff0c\u9ad8\u5149\u548c\u9ad8\u8272\u8c03\u90e8\u5206\u5c42\u6b21\u8f83\u591a\uff0c\u753b\u9762\u8f83\u4e3a\u9510\u5229\u6e05\u6670\uff0c\u753b\u9762\u5404\u5c42\u6b21\u8fc7\u6e21\u81ea\u7136\u3002\u8fd9\u6837\u7684\u5f71\u8c03\u8f6e\u5ed3\u5206\u660e\uff0c\u5177\u6709\u5ba3\u4f20\u753b\u4e00\u6837\u7684\u7279\u5f81\uff0c\u80fd\u591f\u8425\u9020\u6c14\u6c1b\uff0c\u5236\u9020\u60c5\u611f\u57fa\u8c03\uff0c\u63cf\u7ed8\u73b0\u5b9e\u7684\u7ec6\u8282\u7b49\u7b49\u3002\u9002\u5408\u6a21\u7279\u4eba\u50cf\uff0c\u548c\u65c5\u6e38\u6444\u5f71\u3002","color_introductionURL":"https:\/\/beauty-material.adnonstop.com\/API\/interphoto\/dashi_list_wap\/index.php?t=15","color_unlockWeixinImage":"","color_unlockWeixinTitle":"\u603b\u6709\u4e00\u4e2a\u6ee4\u955c\uff0c\u552f\u7f8e\u4e86\u6574\u4e2a\u66fe\u7ecf \u8fd9\u7f8e\u5999\u4e0e\u9707\u64bc\uff0c\u8db3\u4ee5\u8ba9\u4f60\u6ca6\u9677\u5343\u904d\u4e07\u904d","share_link":"https:\/\/beauty-material.adnonstop.com\/share\/interphoto\/filter_share_friend\/index.php?id=43&version=1.2.0","detail":"null","color_filter":{"filter_type":"0","table_pic":"18732017061212025918308996.png","blend":[]}},{"color_ID":"44","color_name":"Corona","type":"0","color_coverImage":"64432016092917313352395133.jpg","color_thumbnailImage":"8010201609291731012044580.jpg","color_alpha":"70","color_coverColor":"6b836b","color_locationType":"-1","color_location":"16","color_statisticalID":"1291030","color_masterType":"0","color_authorImage":"","color_introductionAuthor":"","color_introductionAuthorTitle":"","color_introductionDetail":"","color_introductionURL":"https:\/\/beauty-material.adnonstop.com\/API\/interphoto\/dashi_list_wap\/index.php?t=","color_unlockWeixinImage":"","color_unlockWeixinTitle":"","share_link":"https:\/\/beauty-material.adnonstop.com\/share\/interphoto\/filter_share_friend\/index.php?id=44&version=1.2.0","detail":"null","color_filter":{"filter_type":"0","table_pic":"47462017061212032589117380.png","blend":[]}},{"color_ID":"45","color_name":"Jacaranda","type":"0","color_coverImage":"22532016092917320813580636.jpg","color_thumbnailImage":"22532016092917321375743518.jpg","color_alpha":"70","color_coverColor":"3b4c68","color_locationType":"-1","color_location":"17","color_statisticalID":"1291032","color_masterType":"0","color_authorImage":"","color_introductionAuthor":"","color_introductionAuthorTitle":"","color_introductionDetail":"","color_introductionURL":"https:\/\/beauty-material.adnonstop.com\/API\/interphoto\/dashi_list_wap\/index.php?t=","color_unlockWeixinImage":"","color_unlockWeixinTitle":"","share_link":"https:\/\/beauty-material.adnonstop.com\/share\/interphoto\/filter_share_friend\/index.php?id=45&version=1.2.0","detail":"null","color_filter":{"filter_type":"0","table_pic":"95002017061212034462339763.png","blend":[]}},{"color_ID":"46","color_name":"\u7ea2\u6749","type":"0","color_coverImage":"20782016092917324495116272.jpg","color_thumbnailImage":"48872016092917395427570882.jpg","color_alpha":"70","color_coverColor":"806458","color_locationType":"-1","color_location":"18","color_statisticalID":"1291033","color_masterType":"0","color_authorImage":"","color_introductionAuthor":"","color_introductionAuthorTitle":"","color_introductionDetail":"","color_introductionURL":"https:\/\/beauty-material.adnonstop.com\/API\/interphoto\/dashi_list_wap\/index.php?t=","color_unlockWeixinImage":"","color_unlockWeixinTitle":"","share_link":"https:\/\/beauty-material.adnonstop.com\/share\/interphoto\/filter_share_friend\/index.php?id=46&version=1.2.0","detail":"null","color_filter":{"filter_type":"0","table_pic":"9128201706121204106875591.png","blend":[]}},{"color_ID":"47","color_name":"Aesthetism","type":"0","color_coverImage":"75552016092917351742135858.jpg","color_thumbnailImage":"77142016092917401163764690.jpg","color_alpha":"70","color_coverColor":"2e5bb7","color_locationType":"-1","color_location":"19","color_statisticalID":"1291034","color_masterType":"0","color_authorImage":"","color_introductionAuthor":"","color_introductionAuthorTitle":"","color_introductionDetail":"","color_introductionURL":"https:\/\/beauty-material.adnonstop.com\/API\/interphoto\/dashi_list_wap\/index.php?t=","color_unlockWeixinImage":"","color_unlockWeixinTitle":"","share_link":"https:\/\/beauty-material.adnonstop.com\/share\/interphoto\/filter_share_friend\/index.php?id=47&version=1.2.0","detail":"null","color_filter":{"filter_type":"0","table_pic":"86842017061212042715553455.png","blend":[]}},{"color_ID":"48","color_name":"Alchemy","type":"0","color_coverImage":"40802016092917355341083993.jpg","color_thumbnailImage":"78852016092917402546124047.jpg","color_alpha":"70","color_coverColor":"768b53","color_locationType":"-1","color_location":"20","color_statisticalID":"1291035","color_masterType":"0","color_authorImage":"","color_introductionAuthor":"","color_introductionAuthorTitle":"","color_introductionDetail":"","color_introductionURL":"https:\/\/beauty-material.adnonstop.com\/API\/interphoto\/dashi_list_wap\/index.php?t=","color_unlockWeixinImage":"","color_unlockWeixinTitle":"","share_link":"https:\/\/beauty-material.adnonstop.com\/share\/interphoto\/filter_share_friend\/index.php?id=48&version=1.2.0","detail":"null","color_filter":{"filter_type":"0","table_pic":"69642017061212044633740837.png","blend":[]}},{"color_ID":"49","color_name":"Haze","type":"0","color_coverImage":"90462016092917364623789748.jpg","color_thumbnailImage":"80922016092917404265555455.jpg","color_alpha":"70","color_coverColor":"6b6c62","color_locationType":"-1","color_location":"21","color_statisticalID":"1291037","color_masterType":"0","color_authorImage":"","color_introductionAuthor":"","color_introductionAuthorTitle":"","color_introductionDetail":"","color_introductionURL":"https:\/\/beauty-material.adnonstop.com\/API\/interphoto\/dashi_list_wap\/index.php?t=","color_unlockWeixinImage":"","color_unlockWeixinTitle":"","share_link":"https:\/\/beauty-material.adnonstop.com\/share\/interphoto\/filter_share_friend\/index.php?id=49&version=1.2.0","detail":"null","color_filter":{"filter_type":"1","table_pic":"","blend":[{"blend_pic":"27162017061212051856247535.jpg","blend_alpha":"1.0","blend_type":"45"},{"blend_pic":"33542017061212061218734622.jpg","blend_alpha":"1.0","blend_type":"33"}]}},{"color_ID":"50","color_name":"Taylor","type":"0","color_coverImage":"70782016092917374879550423.jpg","color_thumbnailImage":"18112016092917410150008238.jpg","color_alpha":"70","color_coverColor":"52665b","color_locationType":"-1","color_location":"22","color_statisticalID":"1291039","color_masterType":"0","color_authorImage":"","color_introductionAuthor":"","color_introductionAuthorTitle":"","color_introductionDetail":"","color_introductionURL":"https:\/\/beauty-material.adnonstop.com\/API\/interphoto\/dashi_list_wap\/index.php?t=","color_unlockWeixinImage":"","color_unlockWeixinTitle":"","share_link":"https:\/\/beauty-material.adnonstop.com\/share\/interphoto\/filter_share_friend\/index.php?id=50&version=1.2.0","detail":"null","color_filter":{"filter_type":"0","table_pic":"81732017061212063319239969.png","blend":[]}},{"color_ID":"51","color_name":"\u590f\u5929\u7684\u98ce","type":"0","color_coverImage":"18932016092917381699039826.jpg","color_thumbnailImage":"90772016092917411693938871.jpg","color_alpha":"70","color_coverColor":"98b048","color_locationType":"-1","color_location":"23","color_statisticalID":"1291040","color_masterType":"0","color_authorImage":"","color_introductionAuthor":"","color_introductionAuthorTitle":"","color_introductionDetail":"","color_introductionURL":"https:\/\/beauty-material.adnonstop.com\/API\/interphoto\/dashi_list_wap\/index.php?t=","color_unlockWeixinImage":"","color_unlockWeixinTitle":"","share_link":"https:\/\/beauty-material.adnonstop.com\/share\/interphoto\/filter_share_friend\/index.php?id=51&version=1.2.0","detail":"null","color_filter":{"filter_type":"0","table_pic":"52242017061212070037930085.png","blend":[]}},{"color_ID":"52","color_name":"\u82b1\u6d77","type":"0","color_coverImage":"79942016092917415359321350.jpg","color_thumbnailImage":"7994201609291741572326644.jpg","color_alpha":"70","color_coverColor":"9e282a","color_locationType":"-1","color_location":"24","color_statisticalID":"1291042","color_masterType":"0","color_authorImage":"","color_introductionAuthor":"","color_introductionAuthorTitle":"","color_introductionDetail":"","color_introductionURL":"https:\/\/beauty-material.adnonstop.com\/API\/interphoto\/dashi_list_wap\/index.php?t=","color_unlockWeixinImage":"","color_unlockWeixinTitle":"","share_link":"https:\/\/beauty-material.adnonstop.com\/share\/interphoto\/filter_share_friend\/index.php?id=52&version=1.2.0","detail":"null","color_filter":{"filter_type":"0","table_pic":"92882017061212071773000947.png","blend":[]}},{"color_ID":"53","color_name":"\u5bd2\u51ac","type":"0","color_coverImage":"97872016092917424193025323.jpg","color_thumbnailImage":"6566201609291742491422112.jpg","color_alpha":"70","color_coverColor":"232323","color_locationType":"-1","color_location":"25","color_statisticalID":"1290406","color_masterType":"0","color_authorImage":"","color_introductionAuthor":"","color_introductionAuthorTitle":"","color_introductionDetail":"","color_introductionURL":"https:\/\/beauty-material.adnonstop.com\/API\/interphoto\/dashi_list_wap\/index.php?t=","color_unlockWeixinImage":"","color_unlockWeixinTitle":"","share_link":"https:\/\/beauty-material.adnonstop.com\/share\/interphoto\/filter_share_friend\/index.php?id=53&version=1.2.0","detail":"null","color_filter":{"filter_type":"0","table_pic":"24552017061212074030638925.png","blend":[]}},{"color_ID":"54","color_name":"\u72ec\u767d","type":"0","color_coverImage":"52352016092917433152327716.jpg","color_thumbnailImage":"52352016092917435979556419.jpg","color_alpha":"70","color_coverColor":"000000","color_locationType":"-1","color_location":"26","color_statisticalID":"1290408","color_masterType":"0","color_authorImage":"","color_introductionAuthor":"","color_introductionAuthorTitle":"","color_introductionDetail":"","color_introductionURL":"https:\/\/beauty-material.adnonstop.com\/API\/interphoto\/dashi_list_wap\/index.php?t=","color_unlockWeixinImage":"","color_unlockWeixinTitle":"","share_link":"https:\/\/beauty-material.adnonstop.com\/share\/interphoto\/filter_share_friend\/index.php?id=54&version=1.2.0","detail":"null","color_filter":{"filter_type":"0","table_pic":"20272017061212075721713478.png","blend":[]}},{"color_ID":"55","color_name":"\u8f7b\u6d6e","type":"0","color_coverImage":"53672016092917443938598949.jpg","color_thumbnailImage":"53672016092917444499784231.jpg","color_alpha":"70","color_coverColor":"604556","color_locationType":"-1","color_location":"27","color_statisticalID":"1290410","color_masterType":"0","color_authorImage":"","color_introductionAuthor":"","color_introductionAuthorTitle":"","color_introductionDetail":"","color_introductionURL":"https:\/\/beauty-material.adnonstop.com\/API\/interphoto\/dashi_list_wap\/index.php?t=","color_unlockWeixinImage":"","color_unlockWeixinTitle":"","share_link":"https:\/\/beauty-material.adnonstop.com\/share\/interphoto\/filter_share_friend\/index.php?id=55&version=1.2.0","detail":"null","color_filter":{"filter_type":"0","table_pic":"93132017061212081668439561.png","blend":[]}},{"color_ID":"56","color_name":"\u6e38\u56ed","type":"0","color_coverImage":"78022016092917452390079429.jpg","color_thumbnailImage":"78022016092917453270338994.jpg","color_alpha":"70","color_coverColor":"2492b3","color_locationType":"-1","color_location":"28","color_statisticalID":"1290412","color_masterType":"0","color_authorImage":"","color_introductionAuthor":"","color_introductionAuthorTitle":"","color_introductionDetail":"","color_introductionURL":"https:\/\/beauty-material.adnonstop.com\/API\/interphoto\/dashi_list_wap\/index.php?t=","color_unlockWeixinImage":"","color_unlockWeixinTitle":"","share_link":"https:\/\/beauty-material.adnonstop.com\/share\/interphoto\/filter_share_friend\/index.php?id=56&version=1.2.0","detail":"null","color_filter":{"filter_type":"1","table_pic":"","blend":[{"blend_pic":"63262017061212084266752490.jpg","blend_alpha":"0.7","blend_type":"41"},{"blend_pic":"11982017061212090418148734.jpg","blend_alpha":"0.7","blend_type":"20"}]}},{"color_ID":"57","color_name":"\u82cd\u5c71\u6d77","type":"0","color_coverImage":"93012016092917463862331618.jpg","color_thumbnailImage":"35382016092917464731683583.jpg","color_alpha":"70","color_coverColor":"40665b","color_locationType":"-1","color_location":"29","color_statisticalID":"1290414","color_masterType":"0","color_authorImage":"","color_introductionAuthor":"","color_introductionAuthorTitle":"","color_introductionDetail":"","color_introductionURL":"https:\/\/beauty-material.adnonstop.com\/API\/interphoto\/dashi_list_wap\/index.php?t=","color_unlockWeixinImage":"","color_unlockWeixinTitle":"","share_link":"https:\/\/beauty-material.adnonstop.com\/share\/interphoto\/filter_share_friend\/index.php?id=57&version=1.2.0","detail":"null","color_filter":{"filter_type":"1","table_pic":"","blend":[{"blend_pic":"70102017061212094587104251.jpg","blend_alpha":"0.7","blend_type":"41"},{"blend_pic":"70102017061212100748676786.jpg","blend_alpha":"0.7","blend_type":"20"}]}},{"color_ID":"58","color_name":"\u7f8e\u5473\u60c5\u7f18","type":"0","color_coverImage":"72442016092917473465822469.jpg","color_thumbnailImage":"72442016092917474540202718.jpg","color_alpha":"70","color_coverColor":"eb9e3a","color_locationType":"-1","color_location":"30","color_statisticalID":"1290416","color_masterType":"0","color_authorImage":"","color_introductionAuthor":"","color_introductionAuthorTitle":"","color_introductionDetail":"","color_introductionURL":"https:\/\/beauty-material.adnonstop.com\/API\/interphoto\/dashi_list_wap\/index.php?t=","color_unlockWeixinImage":"","color_unlockWeixinTitle":"","share_link":"https:\/\/beauty-material.adnonstop.com\/share\/interphoto\/filter_share_friend\/index.php?id=58&version=1.2.0","detail":"null","color_filter":{"filter_type":"0","table_pic":"95952017061212103788267019.png","blend":[]}},{"color_ID":"59","color_name":"\u5bc2\u9759","type":"0","color_coverImage":"86082016092917482848939710.jpg","color_thumbnailImage":"86082016092917483170158217.jpg","color_alpha":"70","color_coverColor":"3b2528","color_locationType":"-1","color_location":"31","color_statisticalID":"1290418","color_masterType":"0","color_authorImage":"","color_introductionAuthor":"","color_introductionAuthorTitle":"","color_introductionDetail":"","color_introductionURL":"https:\/\/beauty-material.adnonstop.com\/API\/interphoto\/dashi_list_wap\/index.php?t=","color_unlockWeixinImage":"","color_unlockWeixinTitle":"","share_link":"https:\/\/beauty-material.adnonstop.com\/share\/interphoto\/filter_share_friend\/index.php?id=59&version=1.2.0","detail":"null","color_filter":{"filter_type":"2","table_pic":"54182017061212110735472086.png","blend":[{"blend_pic":"54182017061212111758426995.jpg","blend_alpha":"1.0","blend_type":"33"}]}},{"color_ID":"60","color_name":"Coast","type":"0","color_coverImage":"70002016092917492880691355.jpg","color_thumbnailImage":"70002016092917493188663318.jpg","color_alpha":"70","color_coverColor":"9c9078","color_locationType":"-1","color_location":"32","color_statisticalID":"1291043","color_masterType":"0","color_authorImage":"","color_introductionAuthor":"","color_introductionAuthorTitle":"","color_introductionDetail":"","color_introductionURL":"https:\/\/beauty-material.adnonstop.com\/API\/interphoto\/dashi_list_wap\/index.php?t=","color_unlockWeixinImage":"","color_unlockWeixinTitle":"","share_link":"https:\/\/beauty-material.adnonstop.com\/share\/interphoto\/filter_share_friend\/index.php?id=60&version=1.2.0","detail":"null","color_filter":{"filter_type":"1","table_pic":"","blend":[{"blend_pic":"85012017061212115434515227.jpg","blend_alpha":"1.0","blend_type":"33"}]}},{"color_ID":"63","color_name":"\u82b1\u680f","type":"0","color_coverImage":"26442016092917500867024241.jpg","color_thumbnailImage":"26442016092917501165511148.jpg","color_alpha":"70","color_coverColor":"969c46","color_locationType":"-1","color_location":"33","color_statisticalID":"1290422","color_masterType":"0","color_authorImage":"","color_introductionAuthor":"","color_introductionAuthorTitle":"","color_introductionDetail":"","color_introductionURL":"https:\/\/beauty-material.adnonstop.com\/API\/interphoto\/dashi_list_wap\/index.php?t=","color_unlockWeixinImage":"","color_unlockWeixinTitle":"","share_link":"https:\/\/beauty-material.adnonstop.com\/share\/interphoto\/filter_share_friend\/index.php?id=63&version=1.2.0","detail":"null","color_filter":{"filter_type":"1","table_pic":"","blend":[{"blend_pic":"68602017061212122858925789.jpg","blend_alpha":"1.0","blend_type":"41"}]}},{"color_ID":"64","color_name":"Temptation","type":"0","color_coverImage":"78422016092917510950268573.jpg","color_thumbnailImage":"78422016092917511257704380.jpg","color_alpha":"70","color_coverColor":"8b8182","color_locationType":"-1","color_location":"34","color_statisticalID":"1290424","color_masterType":"0","color_authorImage":"","color_introductionAuthor":"","color_introductionAuthorTitle":"","color_introductionDetail":"","color_introductionURL":"https:\/\/beauty-material.adnonstop.com\/API\/interphoto\/dashi_list_wap\/index.php?t=","color_unlockWeixinImage":"","color_unlockWeixinTitle":"","share_link":"https:\/\/beauty-material.adnonstop.com\/share\/interphoto\/filter_share_friend\/index.php?id=64&version=1.2.0","detail":"null","color_filter":{"filter_type":"2","table_pic":"99492017061212130966265061.png","blend":[{"blend_pic":"99492017061212132035430912.jpg","blend_alpha":"1.0","blend_type":"45"},{"blend_pic":"34982017061212133580022590.jpg","blend_alpha":"1.0","blend_type":"33"}]}},{"color_ID":"65","color_name":"Blues","type":"0","color_coverImage":"63392016092917514788286084.jpg","color_thumbnailImage":"63392016092917515163928733.jpg","color_alpha":"70","color_coverColor":"abbec4","color_locationType":"-1","color_location":"35","color_statisticalID":"1290426","color_masterType":"0","color_authorImage":"","color_introductionAuthor":"","color_introductionAuthorTitle":"","color_introductionDetail":"","color_introductionURL":"https:\/\/beauty-material.adnonstop.com\/API\/interphoto\/dashi_list_wap\/index.php?t=","color_unlockWeixinImage":"","color_unlockWeixinTitle":"","share_link":"https:\/\/beauty-material.adnonstop.com\/share\/interphoto\/filter_share_friend\/index.php?id=65&version=1.2.0","detail":"null","color_filter":{"filter_type":"0","table_pic":"81052017061212140919793617.png","blend":[]}},{"color_ID":"66","color_name":"\u5f52\u5bb6\u8def\u9014","type":"0","color_coverImage":"40962016092917522083841924.jpg","color_thumbnailImage":"98492016092917522760371370.jpg","color_alpha":"70","color_coverColor":"4a2b28","color_locationType":"-1","color_location":"36","color_statisticalID":"1290332","color_masterType":"0","color_authorImage":"","color_introductionAuthor":"","color_introductionAuthorTitle":"","color_introductionDetail":"","color_introductionURL":"https:\/\/beauty-material.adnonstop.com\/API\/interphoto\/dashi_list_wap\/index.php?t=","color_unlockWeixinImage":"","color_unlockWeixinTitle":"","share_link":"https:\/\/beauty-material.adnonstop.com\/share\/interphoto\/filter_share_friend\/index.php?id=66&version=1.2.0","detail":"null","color_filter":{"filter_type":"0","table_pic":"76482017061212143025230419.png","blend":[]}},{"color_ID":"68","color_name":"\u805a\u7126","type":"0","color_coverImage":"32262016092917530792779454.jpg","color_thumbnailImage":"32262016092917532632958582.jpg","color_alpha":"70","color_coverColor":"3f3a39","color_locationType":"-1","color_location":"37","color_statisticalID":"1291044","color_masterType":"0","color_authorImage":"","color_introductionAuthor":"","color_introductionAuthorTitle":"","color_introductionDetail":"","color_introductionURL":"https:\/\/beauty-material.adnonstop.com\/API\/interphoto\/dashi_list_wap\/index.php?t=","color_unlockWeixinImage":"","color_unlockWeixinTitle":"","share_link":"https:\/\/beauty-material.adnonstop.com\/share\/interphoto\/filter_share_friend\/index.php?id=68&version=1.2.0","detail":"null","color_filter":{"filter_type":"1","table_pic":"","blend":[{"blend_pic":"47302017061214043721814148.png","blend_alpha":"0.6","blend_type":"38"}]}},{"color_ID":"69","color_name":"Ash","type":"0","color_coverImage":"46222016092917535849347735.jpg","color_thumbnailImage":"46222016092917540772436855.jpg","color_alpha":"70","color_coverColor":"84798a","color_locationType":"-1","color_location":"39","color_statisticalID":"1290428","color_masterType":"0","color_authorImage":"","color_introductionAuthor":"","color_introductionAuthorTitle":"","color_introductionDetail":"","color_introductionURL":"https:\/\/beauty-material.adnonstop.com\/API\/interphoto\/dashi_list_wap\/index.php?t=","color_unlockWeixinImage":"","color_unlockWeixinTitle":"","share_link":"https:\/\/beauty-material.adnonstop.com\/share\/interphoto\/filter_share_friend\/index.php?id=69&version=1.2.0","detail":"null","color_filter":{"filter_type":"0","table_pic":"37822017061212152717650213.png","blend":[]}},{"color_ID":"70","color_name":"Euro","type":"0","color_coverImage":"11572016092917544593112220.jpg","color_thumbnailImage":"11572016092917545736345492.jpg","color_alpha":"70","color_coverColor":"30433d","color_locationType":"-1","color_location":"40","color_statisticalID":"1291045","color_masterType":"0","color_authorImage":"","color_introductionAuthor":"","color_introductionAuthorTitle":"","color_introductionDetail":"","color_introductionURL":"https:\/\/beauty-material.adnonstop.com\/API\/interphoto\/dashi_list_wap\/index.php?t=","color_unlockWeixinImage":"","color_unlockWeixinTitle":"","share_link":"https:\/\/beauty-material.adnonstop.com\/share\/interphoto\/filter_share_friend\/index.php?id=70&version=1.2.0","detail":"null","color_filter":{"filter_type":"0","table_pic":"59642017061212154613053640.png","blend":[]}}]